simple_password_vault/__init__.py
simple_password_vault/vault.py
simple_password_vault-0.0.1.dist-info/METADATA
simple_password_vault-0.0.1.dist-info/WHEEL
simple_password_vault-0.0.1.dist-info/licenses/LICENSE
simple_password_vault-0.0.1.dist-info/RECORD
