Metadata-Version: 2.3
Name: simple_password_vault
Version: 0.0.1
Summary: A simple Python password manager library
Project-URL: Homepage, https://github.com/huangyunict/simple_password_vault
Project-URL: Issues, https://github.com/huangyunict/simple_password_vault/issues
Author-email: Yun Huang <huangyunict@gmail.com>
License-File: LICENSE
Classifier: License :: OSI Approved :: MIT License
Classifier: Operating System :: OS Independent
Classifier: Programming Language :: Python :: 3
Requires-Python: >=3.8
